{"name":"jQuery fillparent","tagline":"jQuery plugin to make a dom element fill its parent, keeping its original ratio.","body":"## What's that?\r\n\r\njQuery fillparent plugin is a really basic plugin that force a dom element to have the same size as the parent, keeping ots original ratio (overflowing the parent).\r\n\r\nUsefull for image cover style as a css3 fallback.\r\n\r\n> And a fast test for me to publish on [bower](http://bower.io/).\r\n\r\n## Install\r\n\r\nJust call the jquery and jquery.fillparent.min.js javascript file in your html.\r\n\r\nThen read the package [README](https://github.com/tilap/jquery-fillparent/blob/master/README.md) file.","google":"","note":"Don't delete this file! It's used internally to help with page regeneration."}